{
  "MANUFACTURER": "ZTE",
  "MODEL": "Racer",
  "BRAND": "zte",
  "PRODUCT": "racer",
  "DEVICE": "mooncake",
  "RELEASE": "2.3.7",
  "RELEASE_OR_CODENAME": "2.3.7",
  "ID": "GRJ22",
  "INCREMENTAL": "eng..20121231.235229",
  "TYPE": "user",
  "TAGS": "test-keys",
  "FINGERPRINT": "google/passion/passion:2.3.4/GRJ22/121341:user/release-keys",
  "SECURITY_PATCH": "",
  "DEVICE_INITIAL_SDK_INT": 25,
  "SDK_INT": 10,
  "*.build.id": "GRJ22",
  "*.security_patch": "",
  "*api_level": "25",
  "*.build.version.sdk": "10"
}
