{
  "MANUFACTURER": "asus",
  "MODEL": "ME172V",
  "BRAND": "asus",
  "PRODUCT": "WW_me172v",
  "DEVICE": "me172v",
  "RELEASE": "4.1.1",
  "ID": "JRO03H",
  "INCREMENTAL": "WW_me172v-WW_user_4.5.4.16599690_20130326-user-20130326",
  "TYPE": "user",
  "TAGS": "release-keys",
  "FINGERPRINT": "asus/WW_me172v/me172v:4.1.1/JRO03H/WW_user_4.5.4.16599690_20130326:user/release-keys",
  "SECURITY_PATCH": "",
  "DEVICE_INITIAL_SDK_INT": "25",
  "*.build.id": "JRO03H",
  "*.security_patch": "",
  "*api_level": "25"
}
