{
  "MANUFACTURER": "samsung",
  "MODEL": "SM-N9005",
  "BRAND": "samsung",
  "PRODUCT": "hltezh",
  "DEVICE": "hlte",
  "RELEASE": "4.4.2",
  "RELEASE_OR_CODENAME": "4.4.2",
  "ID": "KOT49H",
  "INCREMENTAL": "N9005ZTUENG1",
  "TYPE": "user",
  "TAGS": "release-keys",
  "FINGERPRINT": "samsung/hltezh/hlte:4.4.2/KOT49H/N9005ZTUENG1:user/release-keys",
  "SECURITY_PATCH": "",
  "DEVICE_INITIAL_SDK_INT": 25,
  "SDK_INT": 19,
  "*.build.id": "KOT49H",
  "*.security_patch": "",
  "*api_level": "25",
  "*.build.version.sdk": "19"
}
